LICENSE.txt
setup.cfg
setup.py
tensorrt/__init__.py
tensorrt/plugin/__init__.py
tensorrt/plugin/_autotune.py
tensorrt/plugin/_export.py
tensorrt/plugin/_lib.py
tensorrt/plugin/_plugin_class.py
tensorrt/plugin/_tensor.py
tensorrt/plugin/_top_level.py
tensorrt/plugin/_utils.py
tensorrt/plugin/_validate.py
tensorrt_cu12.egg-info/PKG-INFO
tensorrt_cu12.egg-info/SOURCES.txt
tensorrt_cu12.egg-info/dependency_links.txt
tensorrt_cu12.egg-info/requires.txt
tensorrt_cu12.egg-info/top_level.txt
tensorrt_cu12.egg-info/zip-safe